{
  "parent": "minecraft:recipes/root",
  "criteria": {
    "has_short_sharpened_bone_stick": {
      "conditions": {
        "items": [
          {
            "items": [
              "bonetools:short_sharpened_bone_stick"
            ]
          }
        ]
      },
      "trigger": "minecraft:inventory_changed"
    },
    "has_the_recipe": {
      "conditions": {
        "recipe": "bonetools:bone_dagger"
      },
      "trigger": "minecraft:recipe_unlocked"
    }
  },
  "requirements": [
    [
      "has_short_sharpened_bone_stick",
      "has_the_recipe"
    ]
  ],
  "rewards": {
    "recipes": [
      "bonetools:bone_dagger"
    ]
  },
  "sends_telemetry_event": false
}